erioon/InMemoryInsertOne.py
erioon/InMemoryinsertMany.py
erioon/ai.py
erioon/auth.py
erioon/banner.py
erioon/cli.py
erioon/client.py
erioon/collection.py
erioon/create.py
erioon/database.py
erioon/delete.py
erioon/erioonai.py
erioon/functions.py
erioon/login.py
erioon/ops.py
erioon/ping.py
erioon/playbox.py
erioon/read.py
erioon/sanbox.py
erioon/transaction.py
erioon/update.py
erioon/vector.py
erioon-1.0.2.dist-info/licenses/LICENSE
erioon-1.0.2.dist-info/METADATA
erioon-1.0.2.dist-info/WHEEL
erioon-1.0.2.dist-info/entry_points.txt
erioon-1.0.2.dist-info/top_level.txt
erioon-1.0.2.dist-info/RECORD
