Metadata-Version: 2.4
Name: erioon
Version: 1.0.2
Summary: Erioon Python SDK for seamless interaction with Erioon data services
Author: Zyber Pireci
Author-email: z.pireci@erioon.com
License: MIT
Classifier: Programming Language :: Python :: 3
Classifier: License :: OSI Approved :: MIT License
Classifier: Operating System :: OS Independent
Classifier: Topic :: Software Development :: Libraries
Classifier: Intended Audience :: Developers
Requires-Python: >=3.6
License-File: LICENSE
Requires-Dist: requests>=2.25.1
Requires-Dist: azure-storage-blob>=12.14.1
Requires-Dist: msgpack>=1.0.4
Requires-Dist: scikit-learn>=1.3.0
Requires-Dist: numpy>=1.24.0
Requires-Dist: kubernetes==26.1.0
Requires-Dist: rich>=13.5.2
Requires-Dist: aiohttp
Dynamic: author
Dynamic: author-email
Dynamic: classifier
Dynamic: description
Dynamic: description-content-type
Dynamic: license
Dynamic: license-file
Dynamic: requires-dist
Dynamic: requires-python
Dynamic: summary
